{"ast":null,"code":"/**\n * generates a UID factory\n * @internal\n * @example\n * const uid = generateUID();\n * uid(object) = 1;\n * uid(object) = 1;\n * uid(anotherObject) = 2;\n */\nexport var generateUID = function generateUID() {\n  var counter = 1;\n  var map = new WeakMap();\n  /**\n   * @borrows {uid}\n   */\n\n  var uid = function uid(item, index) {\n    if (typeof item === 'number' || typeof item === 'string') {\n      return index ? \"idx-\" + index : \"val-\" + item;\n    }\n\n    if (!map.has(item)) {\n      map.set(item, counter++);\n      return uid(item);\n    }\n\n    return 'uid' + map.get(item);\n  };\n\n  return uid;\n};\n/**\n * @name uid\n * returns an UID associated with {item}\n * @param {Object} item - object to generate UID for\n * @param {Number} index, a fallback index\n * @example\n * uid(object) == 1;\n * uid(object) == 1;\n * uid(anotherObject) == 2;\n * uid(\"not object\", 42) == 42\n *\n * @see {@link useUID}\n */\n\nexport var uid = generateUID();","map":null,"metadata":{},"sourceType":"module"}